ilertools/__init__.py
ilertools-0.1.0.dist-info/licenses/LICENSE
ilertools-0.1.0.dist-info/METADATA
ilertools-0.1.0.dist-info/WHEEL
ilertools-0.1.0.dist-info/top_level.txt
ilertools-0.1.0.dist-info/RECORD
